lrv/__init__.py
lrv/__main__.py
lrv/cli.py
lrv/daemon.py
lrvd-0.3.0.dist-info/licenses/LICENSE
lrvd-0.3.0.dist-info/licenses/NOTICE
lrvd-0.3.0.dist-info/METADATA
lrvd-0.3.0.dist-info/WHEEL
lrvd-0.3.0.dist-info/entry_points.txt
lrvd-0.3.0.dist-info/top_level.txt
lrvd-0.3.0.dist-info/RECORD
