Metadata-Version: 2.4
Name: lrvd
Version: 0.3.0
Summary: LRV Daemon: LeRobo-Vous - Peer2Peer robot telepresence for LeRobot
Author-email: Daniel Ritchie <daniel@brainwavecollective.ai>
License-Expression: Apache-2.0
Project-URL: Homepage, https://brainwavecollective.ai/
Project-URL: Repository, https://github.com/brainwavecollective/lrv
Project-URL: Issues, https://github.com/brainwavecollective/lrv/issues
Keywords: robotics,robots,teleoperation,telepresence,lerobot,webrtc,remote-control,p2p
Classifier: Development Status :: 3 - Alpha
Classifier: Intended Audience :: Developers
Classifier: Programming Language :: Python :: 3
Classifier: Programming Language :: Python :: 3.8
Classifier: Programming Language :: Python :: 3.9
Classifier: Programming Language :: Python :: 3.10
Classifier: Programming Language :: Python :: 3.11
Classifier: Programming Language :: Python :: 3.12
Classifier: Topic :: Scientific/Engineering :: Artificial Intelligence
Classifier: Topic :: System :: Hardware
Requires-Python: >=3.8
License-File: LICENSE
License-File: NOTICE
Requires-Dist: aiohttp>=3.8.0
Requires-Dist: aiortc>=1.2.0
Requires-Dist: ifaddr>=0.1.7
Requires-Dist: lerobot[feetech]>=0.3.3
Requires-Dist: numpy>=1.20.0
Requires-Dist: opencv-python>=4.5.0
Requires-Dist: tomli>=1.2.0
Requires-Dist: websockets>=10.0
Dynamic: license-file
